fochan/__init__.py
fochan/fc.py
fochan-0.1.0.data/data/share/doc/fochan/README.md
fochan-0.1.0.dist-info/METADATA
fochan-0.1.0.dist-info/RECORD
fochan-0.1.0.dist-info/WHEEL
fochan-0.1.0.dist-info/entry_points.txt
fochan-0.1.0.dist-info/top_level.txt
