Metadata-Version: 2.1
Name: fochan
Version: 0.1.0
Summary: 4chan thread downloader
Home-page: https://github.com/mrfgl/fochan
Author: Maroof
Author-email: i@imrfgl.me
License: UNKNOWN
Platform: UNKNOWN
Classifier: Programming Language :: Python :: 3
Classifier: License :: OSI Approved :: MIT License
Classifier: Operating System :: OS Independent
